pythonwatermark/__init__.py
pythonwatermark/watermarkutils.py
pythonwatermark-0.0.1.dist-info/LICENSE
pythonwatermark-0.0.1.dist-info/METADATA
pythonwatermark-0.0.1.dist-info/WHEEL
pythonwatermark-0.0.1.dist-info/top_level.txt
pythonwatermark-0.0.1.dist-info/zip-safe
pythonwatermark-0.0.1.dist-info/RECORD
