Metadata-Version: 2.1
Name: pythonwatermark
Version: 0.0.1
Summary: Easily add watermarks to PDF, JPG & PNG files with no restrictive licensing
Home-page: https://github.com/bowespublishing/python-watermark
Author: Bowes Publishing
Keywords: watermark,pdf watermark,python watermark
Classifier: Development Status :: 5 - Production/Stable
Classifier: Programming Language :: Python :: 2.7
Classifier: Programming Language :: Python :: 3
Classifier: Programming Language :: Python :: 3.3
Classifier: Programming Language :: Python :: 3.4
Classifier: Programming Language :: Python :: 3.5
Classifier: Programming Language :: Python :: 3.6
Classifier: Intended Audience :: Developers
Classifier: Topic :: Software Development :: Libraries
Classifier: License :: OSI Approved :: MIT License
License-File: LICENSE
Requires-Dist: pypdfium2
Requires-Dist: Pillow
